chatdbg/__init__.py
chatdbg/__main__.py
chatdbg/chatdbg_gdb.py
chatdbg/chatdbg_lldb.py
chatdbg/chatdbg_pdb.py
chatdbg/assistant/__init__.py
chatdbg/assistant/assistant.py
chatdbg/assistant/listeners.py
chatdbg/custom_pdb/prompts.py
chatdbg/custom_pdb/text.py
chatdbg/native_util/clangd_lsp_integration.py
chatdbg/native_util/code.py
chatdbg/native_util/dbg_dialog.py
chatdbg/native_util/safety.py
chatdbg/native_util/stacks.py
chatdbg/pdb_util/capture.py
chatdbg/pdb_util/locals.py
chatdbg/pdb_util/paths.py
chatdbg/pdb_util/sandbox.py
chatdbg/util/config.py
chatdbg/util/exit_message.py
chatdbg/util/help.py
chatdbg/util/history.py
chatdbg/util/jupyter.py
chatdbg/util/log.py
chatdbg/util/markdown.py
chatdbg/util/module_whitelist.txt
chatdbg/util/plog.py
chatdbg/util/printer.py
chatdbg/util/prompts.py
chatdbg/util/stream.py
chatdbg/util/text.py
chatdbg/util/trim.py
chatdbg/util/wrap.py
chatdbg/util/instructions/default.txt
chatdbg/util/instructions/gpt-4o.txt
chatdbg-1.0.1.dist-info/METADATA
chatdbg-1.0.1.dist-info/WHEEL
chatdbg-1.0.1.dist-info/entry_points.txt
chatdbg-1.0.1.dist-info/licenses/LICENSE
chatdbg-1.0.1.dist-info/RECORD
