Metadata-Version: 2.4
Name: ChatDBG
Version: 1.0.1
Summary: AI-assisted debugging. Uses AI to answer 'why'.
Project-URL: Homepage, https://github.com/plasma-umass/ChatDBG
Project-URL: Bug Tracker, https://github.com/plasma-umass/ChatDBG/issues
Author-email: Emery Berger <emery.berger@gmail.com>, Stephen Freund <sfreund@williams.edu>, Kyla Levin <khlevin@umass.edu>, Nicolas van Kempen <nvankemp@gmail.com>
License-File: LICENSE
Classifier: License :: OSI Approved :: Apache Software License
Classifier: Operating System :: OS Independent
Classifier: Programming Language :: Python :: 3
Requires-Python: >=3.9
Requires-Dist: ansicolors>=1.1.8
Requires-Dist: ipdb>=0.13.13
Requires-Dist: ipyflow>=0.0.130
Requires-Dist: ipython==8.18.1
Requires-Dist: litellm==1.55.9
Requires-Dist: llm-utils>=0.2.8
Requires-Dist: numpy>=1.26.3
Requires-Dist: openai>=1.29.0
Requires-Dist: pyyaml>=6.0.1
Requires-Dist: rich>=13.7.0
Requires-Dist: traitlets>=5.14.1
